django_rbac/__init__.py
django_rbac/apps.py
django_rbac/locale/__init__.py
django_rbac/management/__init__.py
django_rbac/migrations/0001_initial.py
django_rbac/migrations/__init__.py
django_rbac/models/__init__.py
django_rbac/models/base.py
django_rbac/models/group.py
django_rbac/models/mixins.py
django_rbac/models/permission.py
django_rbac/models/role.py
django_rbac/models/user.py
django_rbac/tests/__init__.py
django_rbac/utils/__init__.py
examples/__init__.py
django_rbac_auth-0.0.2.dist-info/METADATA
django_rbac_auth-0.0.2.dist-info/WHEEL
django_rbac_auth-0.0.2.dist-info/top_level.txt
django_rbac_auth-0.0.2.dist-info/RECORD
